factionpy/__init__.py
factionpy/api/__init__.py
factionpy/api/queries/__init__.py
factionpy/api/queries/agent_type.py
factionpy/config/__init__.py
factionpy/flask/__init__.py
factionpy/kubernetes/__init__.py
factionpy/logger/__init__.py
factionpy/services/__init__.py
factionpy-2020.8.5.dist-info/METADATA
factionpy-2020.8.5.dist-info/WHEEL
factionpy-2020.8.5.dist-info/top_level.txt
factionpy-2020.8.5.dist-info/RECORD
