Metadata-Version: 2.1
Name: factionpy
Version: 2020.8.5
Summary: Common Library for Python based Faction services.
Home-page: https://github.com/FactionC2/factionpy
Author: The Faction Team
Author-email: team@factionc2.com
License: MIT
Platform: UNKNOWN
Requires-Python: >=3.6
Requires-Dist: bcrypt
Requires-Dist: gql
Requires-Dist: kubernetes
Requires-Dist: pyjwt
